{
    "_links": {
        "self": {
            "href": "http:\/\/default\/taxonomy\/term\/2?_format=hal_json"
        },
        "type": {
            "href": "http:\/\/drupal.org\/rest\/type\/taxonomy_term\/tracks"
        }
    },
    "tid": [
        {
            "value": "2"
        }
    ],
    "uuid": [
        {
            "value": "15d339cc-33f0-4ce1-8297-3b9a4d81b8d2"
        }
    ],
    "langcode": [
        {
            "value": "en",
            "lang": "en"
        }
    ],
    "vid": [
        {
            "target_id": "tracks"
        }
    ],
    "name": [
        {
            "value": "Community",
            "lang": "en"
        }
    ],
    "weight": [
        {
            "value": "0"
        }
    ],
    "changed": [
        {
            "value": "1476889108",
            "lang": "en"
        }
    ],
    "default_langcode": [
        {
            "value": "1",
            "lang": "en"
        }
    ]
}